{
  "cli": {
    "version": ">= 16.0.1",
    "appVersionSource": "remote"
  },
  "build": {
    "base": {
      "node": "20.19.4"
    },
    "development": {
      "extends": "base",
      "developmentClient": true,
      "distribution": "internal"
    },
    "preview": {
      "extends": "base",
      "distribution": "internal",
      "android": {
        "buildType": "apk"
      },
      "env": {
        "EXPO_PUBLIC_APP_ENV": "preview"
      }
    },
    "private-beta": {
      "extends": "base",
      "environment": "production",
      "distribution": "internal",
      "env": {
        "EXPO_PUBLIC_API_URL": "https://hdaugtypjpniesdgyral.supabase.co/functions/v1/horos-api",
        "EXPO_PUBLIC_APP_ENV": "production",
        "EXPO_PUBLIC_ALLOW_DEMO_DATA": "false"
      },
      "android": {
        "buildType": "apk"
      }
    },
    "production": {
      "extends": "base",
      "environment": "production",
      "autoIncrement": true,
      "env": {
        "EXPO_PUBLIC_APP_ENV": "production",
        "EXPO_PUBLIC_ALLOW_DEMO_DATA": "false"
      },
      "android": {
        "buildType": "app-bundle"
      }
    }
  },
  "submit": {
    "production": {}
  }
}
